CHANGELOG.md
LICENSE
README.md
django_db_views/__init__.py
django_db_views/autodetector.py
django_db_views/context_manager.py
django_db_views/db_view.py
django_db_views/fixtures.py
django_db_views/migration_functions.py
django_db_views/operations.py
django_db_views/management/__init__.py
django_db_views/management/commands/__init__.py
django_db_views/management/commands/makeviewmigrations.py
django_db_views-0.1.13.dist-info/METADATA
django_db_views-0.1.13.dist-info/WHEEL
django_db_views-0.1.13.dist-info/licenses/LICENSE
django_db_views-0.1.13.dist-info/RECORD
