Metadata-Version: 2.4
Name: django-db-views
Version: 0.1.13
Summary:     Handle database views.     Allow to create migrations for database views.     View migrations using django code.     They can be reversed.     Changes in model view definition are detected automatically.     Support almost all options as regular makemigrations command
Project-URL: Homepage, https://github.com/BezBartek/django-db-views
Project-URL: Documentation, https://github.com/BezBartek/django-db-views/blob/master/README.md
Project-URL: Repository, https://github.com/BezBartek/django-db-views
Project-URL: Issues, https://github.com/BezBartek/django-db-views/issues
Project-URL: Changelog, https://github.com/BezBartek/django-db-views/blob/master/CHANGELOG.md
Author-email: Bartłomiej Nowak <n.bartek3762@gmail.com>, Mariusz Okulanis <maniek2332@gmail.com>
Maintainer-email: Bartłomiej Nowak <n.bartek3762@gmail.com>
License: MIT License
License-File: LICENSE
Keywords: database perspective,database table function,database views,django,django materialized views,view migrations,views
Classifier: License :: OSI Approved :: MIT License
Classifier: Programming Language :: Python :: 3
Classifier: Programming Language :: Python :: 3.9
Classifier: Programming Language :: Python :: 3.10
Classifier: Programming Language :: Python :: 3.11
Classifier: Programming Language :: Python :: 3.12
Requires-Dist: django>=2.2
Requires-Dist: six
Provides-Extra: dev
Requires-Dist: pre-commit==3.6.0; extra == 'dev'
Provides-Extra: tests
Requires-Dist: build==1.2.1; extra == 'tests'
Requires-Dist: django-environ==0.9.0; extra == 'tests'
Requires-Dist: mysqlclient==2.2.1; extra == 'tests'
Requires-Dist: psycopg2==2.9.3; extra == 'tests'
Requires-Dist: pytest-django==4.5.2; extra == 'tests'
Requires-Dist: pytest-mock==3.8.2; extra == 'tests'
Requires-Dist: tox==3.25.1; extra == 'tests'
